{
    "firefox-gnome-theme": {
        "cargoLocks": null,
        "date": null,
        "extract": null,
        "name": "firefox-gnome-theme",
        "passthru": null,
        "pinned": false,
        "src": {
            "deepClone": false,
            "fetchSubmodules": false,
            "leaveDotGit": false,
            "name": null,
            "rev": "v121",
            "sha256": "sha256-M+Cw6vh7xCDmIhyVuEPNmaNVUwpmdFQq8zlsXZTKees=",
            "type": "git",
            "url": "https://github.com/rafaelmardojai/firefox-gnome-theme"
        },
        "version": "v121"
    },
    "san-francisco-pro": {
        "cargoLocks": null,
        "date": "2021-06-22",
        "extract": null,
        "name": "san-francisco-pro",
        "passthru": null,
        "pinned": false,
        "src": {
            "deepClone": false,
            "fetchSubmodules": false,
            "leaveDotGit": false,
            "name": null,
            "rev": "8bfea09aa6f1139479f80358b2e1e5c6dc991a58",
            "sha256": "sha256-mAXExj8n8gFHq19HfGy4UOJYKVGPYgarGd/04kUIqX4=",
            "type": "git",
            "url": "https://github.com/sahibjotsaggu/San-Francisco-Pro-Fonts"
        },
        "version": "8bfea09aa6f1139479f80358b2e1e5c6dc991a58"
    },
    "waybar": {
        "cargoLocks": null,
        "date": "2023-12-22",
        "extract": null,
        "name": "waybar",
        "passthru": null,
        "pinned": false,
        "src": {
            "deepClone": false,
            "fetchSubmodules": false,
            "leaveDotGit": false,
            "name": null,
            "rev": "d2767fb84ac2efed1c29313dec7ede1b756a6f81",
            "sha256": "sha256-erB32F+3teZexSlBpSrj/oWupKxUxHwrvIACrgvvRvU=",
            "type": "git",
            "url": "https://github.com/alexays/waybar"
        },
        "version": "d2767fb84ac2efed1c29313dec7ede1b756a6f81"
    },
    "wezterm": {
        "cargoLocks": null,
        "date": "2023-12-21",
        "extract": null,
        "name": "wezterm",
        "passthru": null,
        "pinned": false,
        "src": {
            "deepClone": false,
            "fetchSubmodules": true,
            "leaveDotGit": false,
            "name": null,
            "rev": "84ae00c868e711cf97b2bfe885892428f1131a1d",
            "sha256": "sha256-Sx5NtapMe+CtSlW9mfxUHhzF+n9tV2j/St6pku26Rj0=",
            "type": "git",
            "url": "https://github.com/wez/wezterm"
        },
        "version": "84ae00c868e711cf97b2bfe885892428f1131a1d"
    }
}